MANIFEST.in
README.rst
setup.py
PlateReader.egg-info/PKG-INFO
PlateReader.egg-info/SOURCES.txt
PlateReader.egg-info/dependency_links.txt
PlateReader.egg-info/not-zip-safe
PlateReader.egg-info/requires.txt
PlateReader.egg-info/top_level.txt
platereader/__init__.py
platereader/__main__.py
platereader/engine.py
platereader/gui.glade
platereader/gui.py
platereader/my.py
platereader/plateimage.py
platereader/sample.jpg
platereader.egg-info/SOURCES.txt
platereader/docs/manual.pdf