Metadata-Version: 1.0
Name: platereader
Version: 0.2.0
Summary: Software for counting and quantifying colonies on nutrient plates
Home-page: http://github.com/rasmusagren/platereader
Author: Rasmus Agren
Author-email: rasmus@alembic.se
License: GNU General Public License v2.0
Platform: UNKNOWN
